MANIFEST.in
PKG-INFO
doc.html
hello.nt
readme
release_procedure.txt
setup.py
bin/dumpgraph
bin/graphimport
bin/query
bin/sparqlserve
sparqlhttp/__init__.py
sparqlhttp/dictquery.py
sparqlhttp/graph2.py
sparqlhttp/oneshot.py
sparqlhttp/remotegraph.py
sparqlhttp/remotesync.py
sparqlhttp/serve.py
sparqlhttp/sesame.py
sparqlhttp/sesametxn.py
sparqlhttp/sparqljson.py
sparqlhttp/sparqlxml.py
sparqlhttp/stats.py
sparqlhttp/syncimport.py
sparqlhttp.egg-info/PKG-INFO
sparqlhttp.egg-info/SOURCES.txt
sparqlhttp.egg-info/dependency_links.txt
sparqlhttp.egg-info/requires.txt
sparqlhttp.egg-info/top_level.txt
sparqlhttp/test/shared.py
sparqlhttp/test/test_dictquery.py
sparqlhttp/test/test_remotegraph.py
sparqlhttp/test/test_syncimport.py