Metadata-Version: 1.1
Name: sparqlhttp
Version: 1.14
Summary: HTTP SPARQL server and client for twisted and rdflib
Home-page: http://projects.bigasterisk.com/sparqlhttp/
Author: Drew Perttula
Author-email: drewp@bigasterisk.com
License: UNKNOWN
Download-URL: http://projects.bigasterisk.com/sparqlhttp/sparqlhttp-1.14.tar.gz
Platform: UNKNOWN
Classifier: Development Status :: 5 - Production/Stable
Classifier: Intended Audience :: Developers
Classifier: License :: OSI Approved :: GNU Library or Lesser General Public License (LGPL)
Classifier: Programming Language :: Python
Classifier: Topic :: Database
Classifier: Topic :: Internet :: WWW/HTTP
Classifier: Topic :: Software Development :: Libraries :: Python Modules
